{
  "descriptionHash": "BC95D00EAF4F7EAB479792EECDE1E5BBA4221EBAE4D385DFE642258971F51614B38C4C76560A2D46DE6BF27FC67ED439F96778F3D724E0A57C15E1B8C6DB9644",
  "descriptionLocation": "../../../backend/src/PaymentManager.WebApi/PaymentManager.WebApi.json",
  "lockFileVersion": "1.0.0",
  "kiotaVersion": "1.24.0",
  "clientClassName": "PaymentManagerApiClient",
  "typeAccessModifier": "Public",
  "clientNamespaceName": "ApiSdk",
  "language": "TypeScript",
  "usesBackingStore": false,
  "excludeBackwardCompatible": false,
  "includeAdditionalData": true,
  "disableSSLValidation": false,
  "serializers": [
    "Microsoft.Kiota.Serialization.Json.JsonSerializationWriterFactory",
    "Microsoft.Kiota.Serialization.Text.TextSerializationWriterFactory",
    "Microsoft.Kiota.Serialization.Form.FormSerializationWriterFactory",
    "Microsoft.Kiota.Serialization.Multipart.MultipartSerializationWriterFactory"
  ],
  "deserializers": [
    "Microsoft.Kiota.Serialization.Json.JsonParseNodeFactory",
    "Microsoft.Kiota.Serialization.Text.TextParseNodeFactory",
    "Microsoft.Kiota.Serialization.Form.FormParseNodeFactory"
  ],
  "structuredMimeTypes": [
    "application/json",
    "text/plain;q=0.9",
    "application/x-www-form-urlencoded;q=0.2",
    "multipart/form-data;q=0.1"
  ],
  "includePatterns": [],
  "excludePatterns": [],
  "disabledValidationRules": []
}