{
  "descriptionHash": "B93E7FE46AA930B30735F6E7FB4E3F007AE577CC12E3E6315399A6D528D01B770BE828D7D40160FAC1FFA2C213AA928F0732C9EDAF196CE274F26108A473F8B6",
  "descriptionLocation": "../../../../backend/src/PaymentManager.WebApi/PaymentManager.WebApi.json",
  "lockFileVersion": "1.0.0",
  "kiotaVersion": "1.23.0",
  "clientClassName": "PaymentManagerApiClient",
  "typeAccessModifier": "Public",
  "clientNamespaceName": "ApiSdk",
  "language": "TypeScript",
  "usesBackingStore": false,
  "excludeBackwardCompatible": false,
  "includeAdditionalData": true,
  "disableSSLValidation": false,
  "serializers": [
    "Microsoft.Kiota.Serialization.Json.JsonSerializationWriterFactory",
    "Microsoft.Kiota.Serialization.Text.TextSerializationWriterFactory",
    "Microsoft.Kiota.Serialization.Form.FormSerializationWriterFactory",
    "Microsoft.Kiota.Serialization.Multipart.MultipartSerializationWriterFactory"
  ],
  "deserializers": [
    "Microsoft.Kiota.Serialization.Json.JsonParseNodeFactory",
    "Microsoft.Kiota.Serialization.Text.TextParseNodeFactory",
    "Microsoft.Kiota.Serialization.Form.FormParseNodeFactory"
  ],
  "structuredMimeTypes": [
    "application/json",
    "text/plain;q=0.9",
    "application/x-www-form-urlencoded;q=0.2",
    "multipart/form-data;q=0.1"
  ],
  "includePatterns": [],
  "excludePatterns": [],
  "disabledValidationRules": []
}